hari_rr/__init__.py
hari_rr/decision_tree_classifier.py
hari_rr/imports.py
hari_rr/knn.py
hari_rr/linear_regression.py
hari_rr/logistic_regression.py
hari_rr/multivariate_regression.py
hari_rr/performance_metrics.py
hari_rr/random_forest.py
hari_rr/svm.py
hari_rr/xgboost_classifier.py
hari_rr/xgboost_regressor.py
hari_rr-0.1.2.dist-info/METADATA
hari_rr-0.1.2.dist-info/WHEEL
hari_rr-0.1.2.dist-info/top_level.txt
hari_rr-0.1.2.dist-info/RECORD
