Metadata-Version: 2.1
Name: hari-rr
Version: 0.1.2
Summary: A collection of ML algorithms including Decision Trees, SVM, XGBoost, etc.
Home-page: https://github.com/yourusername/hari_rr
Author: HarishaRajan
Author-email: your.email@example.com
Classifier: Programming Language :: Python :: 3
Classifier: License :: OSI Approved :: MIT License
Classifier: Operating System :: OS Independent
Requires-Python: >=3.6
Requires-Dist: numpy
Requires-Dist: pandas
Requires-Dist: matplotlib
